multiprocessing_intenum/__init__.py
multiprocessing_intenum/_version.py
multiprocessing_intenum/py.typed
multiprocessing_intenum-1.0.dist-info/licenses/AUTHORS
multiprocessing_intenum-1.0.dist-info/licenses/LICENSE
multiprocessing_intenum-1.0.dist-info/METADATA
multiprocessing_intenum-1.0.dist-info/WHEEL
multiprocessing_intenum-1.0.dist-info/top_level.txt
multiprocessing_intenum-1.0.dist-info/RECORD
