Metadata-Version: 2.4
Name: multiprocessing-intenum
Version: 1.0
Summary: IntEnumValue type for Python multiprocessing
Author-email: Elmar Hoffmann <elmar.hoffmann@credativ.de>
License-Expression: Apache-2.0
Project-URL: Homepage, https://github.com/credativ/python-multiprocessing-intenum
Project-URL: Github, https://github.com/credativ/python-multiprocessing-intenum
Project-URL: Issues, https://github.com/credativ/python-multiprocessing-intenum/issues
Classifier: Development Status :: 5 - Production/Stable
Classifier: Intended Audience :: Developers
Classifier: Operating System :: OS Independent
Classifier: Programming Language :: Python :: 3
Classifier: Topic :: Software Development :: Libraries :: Python Modules
Classifier: Typing :: Typed
Requires-Python: >=3.8
License-File: LICENSE
License-File: AUTHORS
Dynamic: license-file
